instruqtxblock/__init__.py
instruqtxblock/instruqtxblock.py
instruqtxblock/utils.py
instruqtxblock/locale/__init__.py
instruqtxblock/locale/settings.py
instruqtxblock/settings/test.py
instruqtxblock/static/README.txt
instruqtxblock/static/css/instruqtxblock.css
instruqtxblock/static/html/instruqtxblock.html
instruqtxblock/static/js/src/instruqtxblock.js
instruqt_xblock-0.2.2.dist-info/LICENSE.txt
instruqt_xblock-0.2.2.dist-info/METADATA
instruqt_xblock-0.2.2.dist-info/WHEEL
instruqt_xblock-0.2.2.dist-info/entry_points.txt
instruqt_xblock-0.2.2.dist-info/top_level.txt
instruqt_xblock-0.2.2.dist-info/RECORD
