Metadata-Version: 2.1
Name: instruqt-xblock
Version: 0.2.2
Summary: XBlock to embed Instruqt track in Open edX
Home-page: https://github.com/edly-io/instruqt-xblock
Author: edly
Author-email: admin@edly.io
License: AGPL 3.0
Keywords: Python edx
Platform: UNKNOWN
Classifier: Development Status :: 3 - Alpha
Classifier: Intended Audience :: Developers
Classifier: License :: OSI Approved :: GNU Affero General Public License v3 or later (AGPLv3+)
Classifier: Natural Language :: English
Classifier: Programming Language :: Python :: 3
Classifier: Programming Language :: Python :: 3.5
Requires-Python: >=3.5
License-File: LICENSE.txt
Requires-Dist: Mako
Requires-Dist: XBlock
Requires-Dist: django-statici18n
Requires-Dist: edx-i18n-tools
Requires-Dist: xblock-utils
